joplin_jrnl/__init__.py
joplin_jrnl/main.py
joplin_jrnl-0.3.2.dist-info/entry_points.txt
joplin_jrnl-0.3.2.dist-info/LICENSE
joplin_jrnl-0.3.2.dist-info/WHEEL
joplin_jrnl-0.3.2.dist-info/METADATA
joplin_jrnl-0.3.2.dist-info/RECORD
